debby/__init__.py
debby/__main__.py
debby/args.py
debby/control_file.py
debby/exceptions.py
debby/files.py
debby/meta/__init__.py
debby/meta/meta.py
debby/meta/meta_loader.py
debby/meta/meta_loader_factory.py
debby/meta/poetry_meta_loader.py
debby/meta/pyproject_meta_loader.py
debby/package.py
debby/py.typed
debby/scripts/__init__.py
debby/scripts/script.py
debby/scripts/script_stage.py
debby/scripts/scripts.py
debby-1.2.1.dist-info/LICENSE
debby-1.2.1.dist-info/METADATA
debby-1.2.1.dist-info/WHEEL
debby-1.2.1.dist-info/entry_points.txt
debby-1.2.1.dist-info/RECORD
