Metadata-Version: 2.1
Name: debby
Version: 1.2.1
Summary: Create .deb files easily using python package metadata
Home-page: https://github.com/abrahammurciano/debby
License: GPLv3
Author: Abraham Murciano
Author-email: abrahammurciano@gmail.com
Requires-Python: >=3.8,<4.0
Classifier: License :: Other/Proprietary License
Classifier: Programming Language :: Python :: 3
Classifier: Programming Language :: Python :: 3.8
Classifier: Programming Language :: Python :: 3.9
Classifier: Programming Language :: Python :: 3.10
Classifier: Programming Language :: Python :: 3.11
Classifier: Programming Language :: Python :: 3.12
Classifier: Programming Language :: Python :: 3.13
Requires-Dist: tomli (>=2.0.1,<3.0.0)
Requires-Dist: typing-extensions (>=4.11.0,<5.0.0)
Project-URL: Documentation, https://abrahammurciano.github.io/debby/debby
Project-URL: Repository, https://github.com/abrahammurciano/debby
